u_shape_frame/__init__.py
u_shape_frame/core/__init__.py
u_shape_frame/core/dataflow.cpython-312-darwin.so
u_shape_frame/core/engine.cpython-312-darwin.so
u_shape_frame/core/procession.cpython-312-darwin.so
u_shape_frame/core/processor.cpython-312-darwin.so
u_shape_frame/core/workflow.cpython-312-darwin.so
u_shape_frame/utils/__init__.py
u_shape_frame-0.0.2.dist-info/METADATA
u_shape_frame-0.0.2.dist-info/WHEEL
u_shape_frame-0.0.2.dist-info/top_level.txt
u_shape_frame-0.0.2.dist-info/RECORD
